spectral/__init__.py
spectral/config.py
spectral/image.py
spectral/spectral.py
spectral/algorithms/__init__.py
spectral/algorithms/algorithms.py
spectral/algorithms/classifiers.py
spectral/algorithms/clustering.py
spectral/algorithms/continuum.py
spectral/algorithms/detectors.py
spectral/algorithms/perceptron.py
spectral/algorithms/resampling.py
spectral/algorithms/spatial.py
spectral/algorithms/spymath.py
spectral/algorithms/transforms.py
spectral/database/__init__.py
spectral/database/aster.py
spectral/database/ecostress.py
spectral/database/relab.py
spectral/database/spectral_database.py
spectral/database/usgs.py
spectral/graphics/__init__.py
spectral/graphics/colorscale.py
spectral/graphics/graphics.py
spectral/graphics/hypercube.py
spectral/graphics/ndwindow.py
spectral/graphics/rasterwindow.py
spectral/graphics/spygnuplot.py
spectral/graphics/spypylab.py
spectral/graphics/spywxpython.py
spectral/graphics/spywxpythonthread.py
spectral/io/__init__.py
spectral/io/aviris.py
spectral/io/bilfile.py
spectral/io/bipfile.py
spectral/io/bsqfile.py
spectral/io/envi.py
spectral/io/erdas.py
spectral/io/spyfile.py
spectral/tests/__init__.py
spectral/tests/classifiers.py
spectral/tests/continuum.py
spectral/tests/database.py
spectral/tests/detectors.py
spectral/tests/dimensionality.py
spectral/tests/envi.py
spectral/tests/iterators.py
spectral/tests/memmap.py
spectral/tests/run.py
spectral/tests/spatial.py
spectral/tests/spyfile.py
spectral/tests/spymath.py
spectral/tests/spytest.py
spectral/tests/transforms.py
spectral/tests/data/92AV3C.spc
spectral/tests/data/ecostress/a.spectrum.txt
spectral/tests/data/ecostress/b.spectrum.txt
spectral/tests/data/ecostress/c.spectrum.txt
spectral/tests/data/relab/data/mem/mm/bkr1mm074ws.asc
spectral/tests/data/relab/data/mem/mm/bkr1mm074ws.txt
spectral/tests/data/usgs/ASCIIdata/liba/liba_Bandpass_(FWHM)_ASDFR_SR.txt
spectral/tests/data/usgs/ASCIIdata/liba/liba_Bandpass_(FWHM)_AVIRIS_1996_um.txt
spectral-0.24.dist-info/LICENSE.txt
spectral-0.24.dist-info/METADATA
spectral-0.24.dist-info/WHEEL
spectral-0.24.dist-info/top_level.txt
spectral-0.24.dist-info/RECORD
